debugn/__init__.py
debugn/core.py
debugn/py.typed
debugn-0.1.1.dist-info/METADATA
debugn-0.1.1.dist-info/WHEEL
debugn-0.1.1.dist-info/licenses/LICENSE
debugn-0.1.1.dist-info/RECORD
