Metadata-Version: 2.4
Name: debugn
Version: 0.1.1
Summary: Node.js-style namespace debug logging for Python
Project-URL: Homepage, https://github.com/artfuldev/debugn
Project-URL: Repository, https://github.com/artfuldev/debugn.git
Project-URL: Issues, https://github.com/artfuldev/debugn/issues
Project-URL: Documentation, https://github.com/artfuldev/debugn#readme
Author-email: Sudarsan Balaji <hello@artful.dev>
License: MIT
License-File: LICENSE
Keywords: debug,environment,logging,namespace,node,npm
Classifier: Development Status :: 4 - Beta
Classifier: Environment :: Console
Classifier: Intended Audience :: Developers
Classifier: License :: OSI Approved :: MIT License
Classifier: Operating System :: OS Independent
Classifier: Programming Language :: Python :: 3
Classifier: Programming Language :: Python :: 3.8
Classifier: Programming Language :: Python :: 3.9
Classifier: Programming Language :: Python :: 3.10
Classifier: Programming Language :: Python :: 3.11
Classifier: Programming Language :: Python :: 3.12
Classifier: Programming Language :: Python :: 3.13
Classifier: Topic :: Software Development :: Libraries :: Python Modules
Classifier: Topic :: System :: Logging
Classifier: Typing :: Typed
Requires-Python: >=3.8
